PySimPlot/__init__.py
PySimPlot/alignment.py
PySimPlot/cmd.py
PySimPlot/export.py
PySimPlot/plot.py
PySimPlot/similarity.py
PySimPlot-0.1.1.dist-info/LICENSE
PySimPlot-0.1.1.dist-info/METADATA
PySimPlot-0.1.1.dist-info/WHEEL
PySimPlot-0.1.1.dist-info/entry_points.txt
PySimPlot-0.1.1.dist-info/top_level.txt
PySimPlot-0.1.1.dist-info/RECORD
