Metadata-Version: 2.1
Name: PySimPlot
Version: 0.1.1
Summary: PySimPlot
Author: Jonathan Davies
Author-email: jonathanrd@gmail.com
License: UNKNOWN
Platform: UNKNOWN
Requires-Python: >=3.6
License-File: LICENSE
Requires-Dist: matplotlib (>=3.5.0)
